[{"orderNo":"0D8738D4","costInPence":2400,"outcome":"INVALID_CARD_NUMBER"},{"orderNo":"641ABE70","costInPence":2400,"outcome":"INVALID_EXPIRY_DATE"},{"orderNo":"00FDC1B8","costInPence":2500,"outcome":"INVALID_CVV"},{"orderNo":"79EDF416","costInPence":3108,"outcome":"INVALID_TOTAL"},{"orderNo":"19F13070","costInPence":2400,"outcome":"INVALID_PIZZA_NOT_DEFINED"},{"orderNo":"5CD28092","costInPence":11600,"outcome":"INVALID_PIZZA_COUNT"},{"orderNo":"27894141","costInPence":3900,"outcome":"INVALID_PIZZA_COMBINATION_MULTIPLE_SUPPLIERS"},{"orderNo":"3159C0B5","costInPence":2500,"outcome":"DELIVERED"},{"orderNo":"3D48AB0B","costInPence":2600,"outcome":"VALID_BUT_NOT_DELIVERED"},{"orderNo":"1246D65D","costInPence":2400,"outcome":"DELIVERED"},{"orderNo":"59B40280","costInPence":2400,"outcome":"DELIVERED"},{"orderNo":"583BF0CB","costInPence":2500,"outcome":"DELIVERED"},{"orderNo":"6645B803","costInPence":2600,"outcome":"VALID_BUT_NOT_DELIVERED"},{"orderNo":"59ACB13C","costInPence":2400,"outcome":"DELIVERED"},{"orderNo":"207C1F7F","costInPence":2400,"outcome":"DELIVERED"},{"orderNo":"066CD0F3","costInPence":2500,"outcome":"DELIVERED"},{"orderNo":"027F0521","costInPence":2600,"outcome":"VALID_BUT_NOT_DELIVERED"},{"orderNo":"3D039E87","costInPence":2400,"outcome":"DELIVERED"},{"orderNo":"18663C30","costInPence":2400,"outcome":"DELIVERED"},{"orderNo":"4A23E94E","costInPence":2500,"outcome":"DELIVERED"},{"orderNo":"5FEEF8E1","costInPence":2600,"outcome":"VALID_BUT_NOT_DELIVERED"},{"orderNo":"2F3BF288","costInPence":2400,"outcome":"DELIVERED"},{"orderNo":"71E1A1CF","costInPence":2400,"outcome":"DELIVERED"},{"orderNo":"69F98770","costInPence":2500,"outcome":"DELIVERED"},{"orderNo":"32AB9532","costInPence":2600,"outcome":"VALID_BUT_NOT_DELIVERED"},{"orderNo":"799D4CAB","costInPence":2400,"outcome":"DELIVERED"},{"orderNo":"2D28EE37","costInPence":2400,"outcome":"DELIVERED"},{"orderNo":"581CCD97","costInPence":2500,"outcome":"DELIVERED"},{"orderNo":"62E363C4","costInPence":2600,"outcome":"VALID_BUT_NOT_DELIVERED"},{"orderNo":"16B00742","costInPence":2400,"outcome":"DELIVERED"},{"orderNo":"4E247275","costInPence":2400,"outcome":"DELIVERED"},{"orderNo":"650C4BAE","costInPence":2500,"outcome":"DELIVERED"},{"orderNo":"4AB9A870","costInPence":2600,"outcome":"VALID_BUT_NOT_DELIVERED"},{"orderNo":"27DA0A3A","costInPence":2400,"outcome":"DELIVERED"},{"orderNo":"4BF41A95","costInPence":2400,"outcome":"DELIVERED"},{"orderNo":"671DE614","costInPence":2500,"outcome":"DELIVERED"},{"orderNo":"341EB4B7","costInPence":2600,"outcome":"VALID_BUT_NOT_DELIVERED"},{"orderNo":"193BA44B","costInPence":2400,"outcome":"DELIVERED"},{"orderNo":"1653AE92","costInPence":2400,"outcome":"DELIVERED"},{"orderNo":"3D62C0F0","costInPence":2500,"outcome":"DELIVERED"},{"orderNo":"3AC369E2","costInPence":2600,"outcome":"VALID_BUT_NOT_DELIVERED"},{"orderNo":"6DA6C2E7","costInPence":2400,"outcome":"DELIVERED"},{"orderNo":"459C37DF","costInPence":2400,"outcome":"DELIVERED"},{"orderNo":"0E0980C8","costInPence":2500,"outcome":"DELIVERED"},{"orderNo":"315810E5","costInPence":2600,"outcome":"VALID_BUT_NOT_DELIVERED"},{"orderNo":"3078A27E","costInPence":2400,"outcome":"DELIVERED"},{"orderNo":"415386CC","costInPence":2400,"outcome":"VALID_BUT_NOT_DELIVERED"}]